ledger_bitcoin/__init__.py
ledger_bitcoin/_base58.py
ledger_bitcoin/_script.py
ledger_bitcoin/_serialize.py
ledger_bitcoin/client.py
ledger_bitcoin/client_base.py
ledger_bitcoin/client_command.py
ledger_bitcoin/client_legacy.py
ledger_bitcoin/command_builder.py
ledger_bitcoin/common.py
ledger_bitcoin/errors.py
ledger_bitcoin/key.py
ledger_bitcoin/merkle.py
ledger_bitcoin/psbt.py
ledger_bitcoin/py.typed
ledger_bitcoin/ripemd.py
ledger_bitcoin/segwit_addr.py
ledger_bitcoin/transport.py
ledger_bitcoin/tx.py
ledger_bitcoin/wallet.py
ledger_bitcoin/btchip/__init__.py
ledger_bitcoin/btchip/bitcoinTransaction.py
ledger_bitcoin/btchip/bitcoinVarint.py
ledger_bitcoin/btchip/btchip.py
ledger_bitcoin/btchip/btchipComm.py
ledger_bitcoin/btchip/btchipException.py
ledger_bitcoin/btchip/btchipHelpers.py
ledger_bitcoin/btchip/btchipUtils.py
ledger_bitcoin/btchip/ledgerWrapper.py
ledger_bitcoin/embit/__init__.py
ledger_bitcoin/embit/base.py
ledger_bitcoin/embit/base58.py
ledger_bitcoin/embit/bech32.py
ledger_bitcoin/embit/bip32.py
ledger_bitcoin/embit/compact.py
ledger_bitcoin/embit/ec.py
ledger_bitcoin/embit/hashes.py
ledger_bitcoin/embit/misc.py
ledger_bitcoin/embit/networks.py
ledger_bitcoin/embit/script.py
ledger_bitcoin/embit/descriptor/__init__.py
ledger_bitcoin/embit/descriptor/arguments.py
ledger_bitcoin/embit/descriptor/base.py
ledger_bitcoin/embit/descriptor/checksum.py
ledger_bitcoin/embit/descriptor/descriptor.py
ledger_bitcoin/embit/descriptor/errors.py
ledger_bitcoin/embit/descriptor/miniscript.py
ledger_bitcoin/embit/descriptor/taptree.py
ledger_bitcoin/embit/util/__init__.py
ledger_bitcoin/embit/util/ctypes_secp256k1.py
ledger_bitcoin/embit/util/key.py
ledger_bitcoin/embit/util/py_ripemd160.py
ledger_bitcoin/embit/util/py_secp256k1.py
ledger_bitcoin/embit/util/secp256k1.py
ledger_bitcoin/exception/__init__.py
ledger_bitcoin/exception/device_exception.py
ledger_bitcoin/exception/errors.py
ledger_bitcoin-0.3.0.dist-info/LICENSE
ledger_bitcoin-0.3.0.dist-info/METADATA
ledger_bitcoin-0.3.0.dist-info/WHEEL
ledger_bitcoin-0.3.0.dist-info/top_level.txt
ledger_bitcoin-0.3.0.dist-info/RECORD
