Metadata-Version: 2.1
Name: ledger_bitcoin
Version: 0.3.0
Summary: Client for Ledger Nano Bitcoin application
Home-page: https://github.com/LedgerHQ/app-bitcoin-new
Author: Ledger
Author-email: hello@ledger.fr
Project-URL: Bug Tracker, https://github.com/LedgerHQ/app-bitcoin-new/issues
Classifier: Programming Language :: Python :: 3
Classifier: License :: OSI Approved :: Apache Software License
Classifier: Operating System :: OS Independent
Requires-Python: >=3.7
License-File: LICENSE
Requires-Dist: typing-extensions >=3.7
Requires-Dist: ledgercomm >=1.1.0
Requires-Dist: packaging >=21.3
Provides-Extra: hid
Requires-Dist: hidapi >=0.9.0.post3 ; extra == 'hid'
